Workbook

Sheet Start
A1: Salary Tax-Regime + SIP Goal Planner 2026-27
A2: Kalpa Labs · Kit v1.0 · personal licence
A4: How to use (English)
A5: 1. Tax tab: type your yearly gross salary and age band. Fill the old-regime deductions you really have.
A6: 2. HRA tab: only if you pay rent and get HRA. The result flows into the Tax tab.
A7: 3. The Tax tab shows both regimes, which is lower, and how much you save.
A8: 4. SIP goal tab: a goal, years, and your own return assumption → the monthly SIP to start with.
A9: 5. Loan tab: EMI, and how much interest an extra monthly payment saves.
A10: 6. Self-check tab: every row must say PASS. That proves the formulas match official examples.
A12: ఎలా వాడాలి (తెలుగు)
A13: 1. Tax ట్యాబ్: మీ ఏడాది మొత్తం జీతం, వయసు ఎంచుకోండి. పాత విధానం మినహాయింపులు నిజంగా ఉన్నవే రాయండి.
A14: 2. HRA ట్యాబ్: అద్దె కట్టి HRA వస్తేనే నింపండి. ఫలితం Tax ట్యాబ్‌కు వెళ్తుంది.
... A21: Kalpa Labs · Udyam UDYAM-TS-02-0382711 · aakhiil51458@gmail.com

Sheet Tax
A1: Old vs new regime · 2026-27
A2: Salaried, resident · yellow cells are yours to fill · everything else calculates
A4: Gross salary for the year (₹) | B4: 1300000
A5: Your age band | B5: Below 60
A7: Old regime deductions (the sheet applies the caps) | B7: You enter | C7: Counted
A8: 80C: PF, PPF, ELSS, LIC, tuition… (cap ₹1,50,000) | B8: 150000 | C8: =MIN(MAX(0,B8),150000)
A9: 80D: health insurance (cap ₹1,00,000 incl. parents) | B9: 0 | C9: =MIN(MAX(0,B9),100000)
A10: HRA exemption (from the HRA tab) | B10: =HRA!B12 | C10: =MAX(0,B10)
A11: Home-loan interest, self-occupied (cap ₹2,00,000) | B11: 0 | C11: =MIN(MAX(0,B11),200000)
A12: NPS 80CCD(1B) (cap ₹50,000) | B12: 0 | C12: =MIN(MAX(0,B12),50000)
A13: Other deductions you're sure of | B13: 0 | C13: =MAX(0,B13)
A14: Total old-regime deductions (₹) | C14: =SUM(C8:C13)
B16: New regime | C16: Old regime
A17: Standard deduction (₹) | B17: =Rules!$B$4 | C17: =Rules!$C$4
A18: Taxable income (₹, rounded to ₹10) | B18: =MAX(0,ROUND(($B$4-Rules!$B$4)/10,0)*10) | C18: =MAX(0,ROUND(($B$4-Rules!$C$4-$C$14)/10,0)*10)
A19: Tax on slabs (₹) | B19: =SUMPRODUCT((B18>Rules!$A$9:$A$15)*(B18-Rules!$A$9:$A$15)*Rules!$C$9:$C$15) | C19: =CHOOSE(MATCH($B$5,Rules!$A$27:$A$29,0),SUMPRODUCT((C18>Rules!$A$19:$A$22)*(C18-Rules!$A$19:$A$22)*Rules!$B$19:$B$22),SUMPRODUCT((C18>Rules!$C$19:$C$22)*(C18-Rules!$C$19:$C$22)*Rules!$D$19:$D$22),SUMPRODUCT((C18>Rules!$E$19:$E$22)*(C18-Rules!$E$19:$E$22)*Rules!$F$19:$F$22))
A20: Rebate u/s 156, ex-87A, with marginal relief (₹) | B20: =IF(B18<=Rules!$B$5,MIN(B19,Rules!$B$6),MAX(0,B19-(B18-Rules!$B$5))) | C20: =IF(C18<=Rules!$C$5,MIN(C19,Rules!$C$6),0)
A21: Tax after rebate (₹) | B21: =B19-B20 | C21: =C19-C20
A22: Health and education cess, 4% (₹) | B22: =B21*Rules!$B$7 | C22: =C21*Rules!$B$7
A23: Total tax for the year (₹) | B23: =ROUND((B21+B22)/10,0)*10 | C23: =ROUND((C21+C22)/10,0)*10
A24: Per month (₹) | B24: =ROUND(B23/12,0) | C24: =ROUND(C23/12,0)
A27: Lower tax under | B27: =IF(B23<=C23,"New regime","Old regime")
A28: You save (₹ a year) | B28: =ABS(B23-C23)
A30: Check | B30: =IF(MAX(B18,C18)>5000000,"Income above ₹50 lakh: surcharge isn't included here. Ask a CA.","OK: within this kit's range")
A32: This is a calculator, not tax advice. It names no investments and makes no return promises.

Sheet HRA
A1: HRA exemption (old regime only)
A2: Yearly amounts · the smallest of three limits is exempt
A4: Basic + DA for the year (₹) | B4: 600000
A5: HRA received for the year (₹) | B5: 240000
A6: Rent paid for the year (₹) | B6: 240000
A7: City you live in | B7: Hyderabad
A9: 1. HRA actually received | B9: =B5
A10: 2. 50% of basic+DA (metro) or 40% (other city) | B10: =B4*IF(B7="Other city",0.4,0.5)
A11: 3. Rent paid minus 10% of basic+DA | B11: =MAX(0,B6-0.1*B4)
A12: HRA exempt (smallest of 1, 2, 3) (₹) | B12: =ROUND(MAX(0,MIN(B9,B10,B11)),0)
A13: HRA that stays taxable (₹) | B13: =ROUND(B5-B12,0)
A15: Goes to the Tax tab automatically. Claim it only in the old regime, with rent receipts (and the landlord's PAN above ₹1 lakh rent a year).

Sheet SIP goal
A1: SIP goal planner
A2: How much to invest each month, with a yearly step-up · returns are your assumption, not a promise
A4: Goal in today's money (₹) | B4: 2000000
A5: Years to the goal | B5: 10
A6: Inflation a year | B6: 0.06
A7: Return you assume a year | B7: 0.1
A8: Increase your SIP every year by | B8: 0.1
A9: Money already saved for it (₹) | B9: 0
A11: Goal in future money (₹) | B11: =B4*(1+B6)^B5
A12: Your savings will grow to (₹) | B12: =B9*(1+B7)^B5
A13: Still needed (₹) | B13: =MAX(0,B11-B12)
A14: ₹1 a month this year grows to (₹) | B14: =SUM(D20:D59)
A15: Start your SIP at (₹ a month, rounded up to ₹100) | B15: =IF(B14=0,0,CEILING(B13/B14,100))
A16: Check | B16: =IF(OR(B5<1,B5>40),"Use 1 to 40 years","OK")
A19: Year | B19: Monthly SIP this year (₹) | C19: Step-up factor | D19: ₹1/month factor at the goal
A20: 1 | B20: =IF(A20<=$B$5,ROUND($B$15*C20,0),"") | C20: =IF(A20<=$B$5,(1+$B$8)^(A20-1),0) | D20: =IF(A20<=$B$5,C20*IF($B$7=0,12,((1+$B$7/12)^12-1)/($B$7/12)*(1+$B$7/12))*(1+$B$7/12)^(12*($B$5-A20)),0)
A21: 2 | B21: =IF(A21<=$B$5,ROUND($B$15*C21,0),"") | C21: =IF(A21<=$B$5,(1+$B$8)^(A21-1),0) | D21: =IF(A21<=$B$5,C21*IF($B$7=0,12,((1+$B$7/12)^12-1)/($B$7/12)*(1+$B$7/12))*(1+$B$7/12)^(12*($B$5-A21)),0)
A22: 3 | B22: =IF(A22<=$B$5,ROUND($B$15*C22,0),"") | C22: =IF(A22<=$B$5,(1+$B$8)^(A22-1),0) | D22: =IF(A22<=$B$5,C22*IF($B$7=0,12,((1+$B$7/12)^12-1)/($B$7/12)*(1+$B$7/12))*(1+$B$7/12)^(12*($B$5-A22)),0)
A23: 4 | B23: =IF(A23<=$B$5,ROUND($B$15*C23,0),"") | C23: =IF(A23<=$B$5,(1+$B$8)^(A23-1),0) | D23: =IF(A23<=$B$5,C23*IF($B$7=0,12,((1+$B$7/12)^12-1)/($B$7/12)*(1+$B$7/12))*(1+$B$7/12)^(12*($B$5-A23)),0)
A24: 5 | B24: =IF(A24<=$B$5,ROUND($B$15*C24,0),"") | C24: =IF(A24<=$B$5,(1+$B$8)^(A24-1),0) | D24: =IF(A24<=$B$5,C24*IF($B$7=0,12,((1+$B$7/12)^12-1)/($B$7/12)*(1+$B$7/12))*(1+$B$7/12)^(12*($B$5-A24)),0)
A25: 6 | B25: =IF(A25<=$B$5,ROUND($B$15*C25,0),"") | C25: =IF(A25<=$B$5,(1+$B$8)^(A25-1),0) | D25: =IF(A25<=$B$5,C25*IF($B$7=0,12,((1+$B$7/12)^12-1)/($B$7/12)*(1+$B$7/12))*(1+$B$7/12)^(12*($B$5-A25)),0)
A26: 7 | B26: =IF(A26<=$B$5,ROUND($B$15*C26,0),"") | C26: =IF(A26<=$B$5,(1+$B$8)^(A26-1),0) | D26: =IF(A26<=$B$5,C26*IF($B$7=0,12,((1+$B$7/12)^12-1)/($B$7/12)*(1+$B$7/12))*(1+$B$7/12)^(12*($B$5-A26)),0)
A27: 8 | B27: =IF(A27<=$B$5,ROUND($B$15*C27,0),"") | C27: =IF(A27<=$B$5,(1+$B$8)^(A27-1),0) | D27: =IF(A27<=$B$5,C27*IF($B$7=0,12,((1+$B$7/12)^12-1)/($B$7/12)*(1+$B$7/12))*(1+$B$7/12)^(12*($B$5-A27)),0)
A28: 9 | B28: =IF(A28<=$B$5,ROUND($B$15*C28,0),"") | C28: =IF(A28<=$B$5,(1+$B$8)^(A28-1),0) | D28: =IF(A28<=$B$5,C28*IF($B$7=0,12,((1+$B$7/12)^12-1)/($B$7/12)*(1+$B$7/12))*(1+$B$7/12)^(12*($B$5-A28)),0)
A29: 10 | B29: =IF(A29<=$B$5,ROUND($B$15*C29,0),"") | C29: =IF(A29<=$B$5,(1+$B$8)^(A29-1),0) | D29: =IF(A29<=$B$5,C29*IF($B$7=0,12,((1+$B$7/12)^12-1)/($B$7/12)*(1+$B$7/12))*(1+$B$7/12)^(12*($B$5-A29)),0)
A30: 11 | B30: =IF(A30<=$B$5,ROUND($B$15*C30,0),"") | C30: =IF(A30<=$B$5,(1+$B$8)^(A30-1),0) | D30: =IF(A30<=$B$5,C30*IF($B$7=0,12,((1+$B$7/12)^12-1)/($B$7/12)*(1+$B$7/12))*(1+$B$7/12)^(12*($B$5-A30)),0)
A31: 12 | B31: =IF(A31<=$B$5,ROUND($B$15*C31,0),"") | C31: =IF(A31<=$B$5,(1+$B$8)^(A31-1),0) | D31: =IF(A31<=$B$5,C31*IF($B$7=0,12,((1+$B$7/12)^12-1)/($B$7/12)*(1+$B$7/12))*(1+$B$7/12)^(12*($B$5-A31)),0)
... A59: 40 | B59: =IF(A59<=$B$5,ROUND($B$15*C59,0),"") | C59: =IF(A59<=$B$5,(1+$B$8)^(A59-1),0) | D59: =IF(A59<=$B$5,C59*IF($B$7=0,12,((1+$B$7/12)^12-1)/($B$7/12)*(1+$B$7/12))*(1+$B$7/12)^(12*($B$5-A59)),0)

Sheet Loan
A1: Loan EMI and prepayment
A2: Reducing balance, the way banks calculate it · up to 30 years
A4: Loan amount (₹) | B4: 3000000
A5: Interest rate a year | B5: 0.085
A6: Years | B6: 20
A7: Extra you'll pay every month (₹) | B7: 5000
A9: EMI (₹ a month) | B9: =ROUND(PMT(B5/12,B6*12,-B4),0)
A10: Total interest without prepaying (₹) | B10: =ROUND(PMT(B5/12,B6*12,-B4)*B6*12-B4,0)
A11: Total interest with the extra payment (₹) | B11: =ROUND(SUM(C17:C376),0)
A12: Interest you save (₹) | B12: =B10-B11
A13: Months you finish early | B13: =B6*12-COUNTIF(C17:C376,">0")
A14: Prepaying saves the interest above. Investing the extra instead may earn more or less: compare with your SIP tab's assumed return.
A16: Month | B16: Balance at start (₹) | C16: Interest (₹) | D16: Balance at end (₹)
A17: 1 | B17: =$B$4 | C17: =IF(AND(B17>0,A17<=$B$6*12),B17*$B$5/12,0) | D17: =IF(B17>0,MAX(0,B17-(PMT($B$5/12,$B$6*12,-$B$4)-C17+$B$7)),0)
A18: 2 | B18: =D17 | C18: =IF(AND(B18>0,A18<=$B$6*12),B18*$B$5/12,0) | D18: =IF(B18>0,MAX(0,B18-(PMT($B$5/12,$B$6*12,-$B$4)-C18+$B$7)),0)
A19: 3 | B19: =D18 | C19: =IF(AND(B19>0,A19<=$B$6*12),B19*$B$5/12,0) | D19: =IF(B19>0,MAX(0,B19-(PMT($B$5/12,$B$6*12,-$B$4)-C19+$B$7)),0)
A20: 4 | B20: =D19 | C20: =IF(AND(B20>0,A20<=$B$6*12),B20*$B$5/12,0) | D20: =IF(B20>0,MAX(0,B20-(PMT($B$5/12,$B$6*12,-$B$4)-C20+$B$7)),0)
A21: 5 | B21: =D20 | C21: =IF(AND(B21>0,A21<=$B$6*12),B21*$B$5/12,0) | D21: =IF(B21>0,MAX(0,B21-(PMT($B$5/12,$B$6*12,-$B$4)-C21+$B$7)),0)
A22: 6 | B22: =D21 | C22: =IF(AND(B22>0,A22<=$B$6*12),B22*$B$5/12,0) | D22: =IF(B22>0,MAX(0,B22-(PMT($B$5/12,$B$6*12,-$B$4)-C22+$B$7)),0)
A23: 7 | B23: =D22 | C23: =IF(AND(B23>0,A23<=$B$6*12),B23*$B$5/12,0) | D23: =IF(B23>0,MAX(0,B23-(PMT($B$5/12,$B$6*12,-$B$4)-C23+$B$7)),0)
A24: 8 | B24: =D23 | C24: =IF(AND(B24>0,A24<=$B$6*12),B24*$B$5/12,0) | D24: =IF(B24>0,MAX(0,B24-(PMT($B$5/12,$B$6*12,-$B$4)-C24+$B$7)),0)
A25: 9 | B25: =D24 | C25: =IF(AND(B25>0,A25<=$B$6*12),B25*$B$5/12,0) | D25: =IF(B25>0,MAX(0,B25-(PMT($B$5/12,$B$6*12,-$B$4)-C25+$B$7)),0)
A26: 10 | B26: =D25 | C26: =IF(AND(B26>0,A26<=$B$6*12),B26*$B$5/12,0) | D26: =IF(B26>0,MAX(0,B26-(PMT($B$5/12,$B$6*12,-$B$4)-C26+$B$7)),0)
A27: 11 | B27: =D26 | C27: =IF(AND(B27>0,A27<=$B$6*12),B27*$B$5/12,0) | D27: =IF(B27>0,MAX(0,B27-(PMT($B$5/12,$B$6*12,-$B$4)-C27+$B$7)),0)
A28: 12 | B28: =D27 | C28: =IF(AND(B28>0,A28<=$B$6*12),B28*$B$5/12,0) | D28: =IF(B28>0,MAX(0,B28-(PMT($B$5/12,$B$6*12,-$B$4)-C28+$B$7)),0)
A29: 13 | B29: =D28 | C29: =IF(AND(B29>0,A29<=$B$6*12),B29*$B$5/12,0) | D29: =IF(B29>0,MAX(0,B29-(PMT($B$5/12,$B$6*12,-$B$4)-C29+$B$7)),0)
... A376: 360 | B376: =D375 | C376: =IF(AND(B376>0,A376<=$B$6*12),B376*$B$5/12,0) | D376: =IF(B376>0,MAX(0,B376-(PMT($B$5/12,$B$6*12,-$B$4)-C376+$B$7)),0)

Sheet Self-check
A1: Self-check: this sheet against official examples
A2: Every row runs the same formulas as the Tax tab · all rows must say PASS
A4: Gross (₹) | B4: Deductions (₹) | C4: Age | D4: New: sheet | E4: New: expected | F4: Old: sheet | G4: Old: expected | H4: Result
A5: 1275000 | B5: 150000 | C5: Below 60 | D5: =B1006 | E5: 0 | F5: =C1006 | G5: 140400 | H5: =IF(AND(D5=E5,F5=G5),"PASS","FAIL")
A6: 1300000 | B6: 150000 | C6: Below 60 | D6: =B1016 | E6: 26000 | F6: =C1016 | G6: 148200 | H6: =IF(AND(D6=E6,F6=G6),"PASS","FAIL")
A7: 2500000 | B7: 150000 | C7: Below 60 | D7: =B1026 | E7: 319800 | F7: =C1026 | G7: 522600 | H7: =IF(AND(D7=E7,F7=G7),"PASS","FAIL")
A9: Expected values: tax year 2026-27, salaried below 60, old regime with ₹1,50,000 deductions (india-tax-guru fixtures, MIT).
A1000: Standard deduction (₹) | B1000: =Rules!$B$4 | C1000: =Rules!$C$4
A1001: Taxable income (₹, rounded to ₹10) | B1001: =MAX(0,ROUND(($A$5-Rules!$B$4)/10,0)*10) | C1001: =MAX(0,ROUND(($A$5-Rules!$C$4-$B$5)/10,0)*10)
A1002: Tax on slabs (₹) | B1002: =SUMPRODUCT((B1001>Rules!$A$9:$A$15)*(B1001-Rules!$A$9:$A$15)*Rules!$C$9:$C$15) | C1002: =CHOOSE(MATCH($C$5,Rules!$A$27:$A$29,0),SUMPRODUCT((C1001>Rules!$A$19:$A$22)*(C1001-Rules!$A$19:$A$22)*Rules!$B$19:$B$22),SUMPRODUCT((C1001>Rules!$C$19:$C$22)*(C1001-Rules!$C$19:$C$22)*Rules!$D$19:$D$22),SUMPRODUCT((C1001>Rules!$E$19:$E$22)*(C1001-Rules!$E$19:$E$22)*Rules!$F$19:$F$22))
A1003: Rebate u/s 156, ex-87A, with marginal relief (₹) | B1003: =IF(B1001<=Rules!$B$5,MIN(B1002,Rules!$B$6),MAX(0,B1002-(B1001-Rules!$B$5))) | C1003: =IF(C1001<=Rules!$C$5,MIN(C1002,Rules!$C$6),0)
A1004: Tax after rebate (₹) | B1004: =B1002-B1003 | C1004: =C1002-C1003
A1005: Health and education cess, 4% (₹) | B1005: =B1004*Rules!$B$7 | C1005: =C1004*Rules!$B$7
A1006: Total tax for the year (₹) | B1006: =ROUND((B1004+B1005)/10,0)*10 | C1006: =ROUND((C1004+C1005)/10,0)*10
A1007: Per month (₹) | B1007: =ROUND(B1006/12,0) | C1007: =ROUND(C1006/12,0)
A1010: Standard deduction (₹) | B1010: =Rules!$B$4 | C1010: =Rules!$C$4
A1011: Taxable income (₹, rounded to ₹10) | B1011: =MAX(0,ROUND(($A$6-Rules!$B$4)/10,0)*10) | C1011: =MAX(0,ROUND(($A$6-Rules!$C$4-$B$6)/10,0)*10)
A1012: Tax on slabs (₹) | B1012: =SUMPRODUCT((B1011>Rules!$A$9:$A$15)*(B1011-Rules!$A$9:$A$15)*Rules!$C$9:$C$15) | C1012: =CHOOSE(MATCH($C$6,Rules!$A$27:$A$29,0),SUMPRODUCT((C1011>Rules!$A$19:$A$22)*(C1011-Rules!$A$19:$A$22)*Rules!$B$19:$B$22),SUMPRODUCT((C1011>Rules!$C$19:$C$22)*(C1011-Rules!$C$19:$C$22)*Rules!$D$19:$D$22),SUMPRODUCT((C1011>Rules!$E$19:$E$22)*(C1011-Rules!$E$19:$E$22)*Rules!$F$19:$F$22))
A1013: Rebate u/s 156, ex-87A, with marginal relief (₹) | B1013: =IF(B1011<=Rules!$B$5,MIN(B1012,Rules!$B$6),MAX(0,B1012-(B1011-Rules!$B$5))) | C1013: =IF(C1011<=Rules!$C$5,MIN(C1012,Rules!$C$6),0)
A1014: Tax after rebate (₹) | B1014: =B1012-B1013 | C1014: =C1012-C1013
A1015: Health and education cess, 4% (₹) | B1015: =B1014*Rules!$B$7 | C1015: =C1014*Rules!$B$7
A1016: Total tax for the year (₹) | B1016: =ROUND((B1014+B1015)/10,0)*10 | C1016: =ROUND((C1014+C1015)/10,0)*10
A1017: Per month (₹) | B1017: =ROUND(B1016/12,0) | C1017: =ROUND(C1016/12,0)
A1020: Standard deduction (₹) | B1020: =Rules!$B$4 | C1020: =Rules!$C$4
A1021: Taxable income (₹, rounded to ₹10) | B1021: =MAX(0,ROUND(($A$7-Rules!$B$4)/10,0)*10) | C1021: =MAX(0,ROUND(($A$7-Rules!$C$4-$B$7)/10,0)*10)
A1022: Tax on slabs (₹) | B1022: =SUMPRODUCT((B1021>Rules!$A$9:$A$15)*(B1021-Rules!$A$9:$A$15)*Rules!$C$9:$C$15) | C1022: =CHOOSE(MATCH($C$7,Rules!$A$27:$A$29,0),SUMPRODUCT((C1021>Rules!$A$19:$A$22)*(C1021-Rules!$A$19:$A$22)*Rules!$B$19:$B$22),SUMPRODUCT((C1021>Rules!$C$19:$C$22)*(C1021-Rules!$C$19:$C$22)*Rules!$D$19:$D$22),SUMPRODUCT((C1021>Rules!$E$19:$E$22)*(C1021-Rules!$E$19:$E$22)*Rules!$F$19:$F$22))
A1023: Rebate u/s 156, ex-87A, with marginal relief (₹) | B1023: =IF(B1021<=Rules!$B$5,MIN(B1022,Rules!$B$6),MAX(0,B1022-(B1021-Rules!$B$5))) | C1023: =IF(C1021<=Rules!$C$5,MIN(C1022,Rules!$C$6),0)
A1024: Tax after rebate (₹) | B1024: =B1022-B1023 | C1024: =C1022-C1023
A1025: Health and education cess, 4% (₹) | B1025: =B1024*Rules!$B$7 | C1025: =C1024*Rules!$B$7
A1026: Total tax for the year (₹) | B1026: =ROUND((B1024+B1025)/10,0)*10 | C1026: =ROUND((C1024+C1025)/10,0)*10
A1027: Per month (₹) | B1027: =ROUND(B1026/12,0) | C1027: =ROUND(C1026/12,0)

Sheet Rules
A1: Rules used (tax year 2026-27)
A2: Income-tax Act 2025 · checked 16 Oct 2026 · don't edit unless the law changes
B3: New regime | C3: Old regime
A4: Standard deduction for salaried (₹) | B4: 75000 | C4: 50000
A5: Rebate: taxable income up to (₹) | B5: 1200000 | C5: 500000
A6: Rebate: maximum (₹) | B6: 60000 | C6: 12500
A7: Cess | B7: 0.04 | C7: 0.04
A8: New regime slabs: from (₹) · rate · rate step
A9: 0 | B9: 0 | C9: 0
A10: 400000 | B10: 0.05 | C10: 0.05
A11: 800000 | B11: 0.1 | C11: 0.05
A12: 1200000 | B12: 0.15 | C12: 0.05
A13: 1600000 | B13: 0.2 | C13: 0.05
A14: 2000000 | B14: 0.25 | C14: 0.05
A15: 2400000 | B15: 0.3 | C15: 0.05
A17: Old regime slabs by age: from (₹) · rate step
A18: Below 60 | C18: 60 to 80 | E18: 80 and above
A19: 0 | B19: 0 | C19: 0 | D19: 0 | E19: 0 | F19: 0
A20: 250000 | B20: 0.05 | C20: 300000 | D20: 0.05 | E20: 500000 | F20: 0.2
A21: 500000 | B21: 0.15 | C21: 500000 | D21: 0.15 | E21: 1000000 | F21: 0.1
A22: 1000000 | B22: 0.1 | C22: 1000000 | D22: 0.1 | E22: 1e+15 | F22: 0
A26: Age bands (for the drop-down)
A27: Below 60
A28: 60 to 80
A29: 80 and above
A31: HRA: metro cities that get the 50% limit (2026-27)
A32: Delhi
A33: Mumbai
A34: Chennai
A35: Kolkata
A36: Bengaluru
A37: Hyderabad
A38: Pune
... A42: Sources: Finance Bill 2026 memorandum (no change in rates); incometaxindia.gov.in tax rates; Income-tax Act 2025. Surcharge above ₹50 lakh is not included in this kit.
